pyibex-1.9.2.data/purelib/pyibex/__init__.py
pyibex-1.9.2.data/purelib/pyibex/minkowsky_ops.py
pyibex-1.9.2.data/purelib/pyibex/paving.pyd
pyibex-1.9.2.data/purelib/pyibex/perftools.py
pyibex-1.9.2.data/purelib/pyibex/pySepPaving.py
pyibex-1.9.2.data/purelib/pyibex/pyibex.pyd
pyibex-1.9.2.data/purelib/pyibex/pysivia.py
pyibex-1.9.2.data/purelib/pyibex/septotikz.py
pyibex-1.9.2.data/purelib/pyibex/sepvisitor.py
pyibex-1.9.2.data/purelib/pyibex/version.py
pyibex-1.9.2.data/purelib/pyibex/examples/Catan2.py
pyibex-1.9.2.data/purelib/pyibex/examples/__init__.py
pyibex-1.9.2.data/purelib/pyibex/examples/ex_ctcRaster.py
pyibex-1.9.2.data/purelib/pyibex/examples/example1.py
pyibex-1.9.2.data/purelib/pyibex/examples/example2.py
pyibex-1.9.2.data/purelib/pyibex/examples/example3.py
pyibex-1.9.2.data/purelib/pyibex/examples/example_paving_transform.py
pyibex-1.9.2.data/purelib/pyibex/examples/example_polar.py
pyibex-1.9.2.data/purelib/pyibex/examples/example_projection1.py
pyibex-1.9.2.data/purelib/pyibex/examples/sphereProj.py
pyibex-1.9.2.data/purelib/pyibex/examples/test_Img.py
pyibex-1.9.2.data/purelib/pyibex/geometry/__init__.py
pyibex-1.9.2.data/purelib/pyibex/geometry/geometry.pyd
pyibex-1.9.2.data/purelib/pyibex/image/__init__.py
pyibex-1.9.2.data/purelib/pyibex/image/image.pyd
pyibex-1.9.2.data/purelib/pyibex/polar/__init__.py
pyibex-1.9.2.data/purelib/pyibex/tests/__init__.py
pyibex-1.9.2.data/purelib/pyibex/tests/test_Bsc.py
pyibex-1.9.2.data/purelib/pyibex/tests/test_Catan2.py
pyibex-1.9.2.data/purelib/pyibex/tests/test_Contractors.py
pyibex-1.9.2.data/purelib/pyibex/tests/test_CustomCtc.py
pyibex-1.9.2.data/purelib/pyibex/tests/test_Interval.py
pyibex-1.9.2.data/purelib/pyibex/tests/test_IntervalMatrix.py
pyibex-1.9.2.data/purelib/pyibex/tests/test_IntervalVector.py
pyibex-1.9.2.data/purelib/pyibex/tests/test_SepPaving.py
pyibex-1.9.2.data/purelib/pyibex/tests/test_Separators.py
pyibex-1.9.2.data/purelib/pyibex/tests/test_image.py
pyibex-1.9.2.dist-info/METADATA
pyibex-1.9.2.dist-info/WHEEL
pyibex-1.9.2.dist-info/top_level.txt
pyibex-1.9.2.dist-info/RECORD
