Metadata-Version: 2.1
Name: pyibex
Version: 1.9.2
Summary: PyIbex a python interface of ibexlib 
Home-page: https://github.com/benEnsta/pyIbex
Author: Benoit Desrochers
Author-email: ben.ensta@gmail.com
License: LGPLv3+
Platform: UNKNOWN
Classifier: Development Status :: 3 - Alpha
Classifier: Topic :: Scientific/Engineering :: Mathematics
Classifier: License :: OSI Approved :: GNU Lesser General Public License v3 or later (LGPLv3+)
Requires-Dist: vibes
